nonebot_plugin_chatgpt_diy/__init__.py
nonebot_plugin_chatgpt_diy/config.py
nonebot_plugin_chatgpt_diy/model.py
nonebot_plugin_chatgpt_diy-0.1.1.dist-info/LICENSE
nonebot_plugin_chatgpt_diy-0.1.1.dist-info/METADATA
nonebot_plugin_chatgpt_diy-0.1.1.dist-info/WHEEL
nonebot_plugin_chatgpt_diy-0.1.1.dist-info/top_level.txt
nonebot_plugin_chatgpt_diy-0.1.1.dist-info/RECORD
